.project
.pydevproject
CHANGES.rst
MANIFEST.in
README.rst
bootstrap.py
buildout.cfg
setup.cfg
setup.py
.externalToolBuilders/org.python.pydev.PyDevBuilder.launch
.settings/org.eclipse.core.resources.prefs
tlspu/__init__.py
tlspu.cookiepolicy.egg-info/PKG-INFO
tlspu.cookiepolicy.egg-info/SOURCES.txt
tlspu.cookiepolicy.egg-info/dependency_links.txt
tlspu.cookiepolicy.egg-info/entry_points.txt
tlspu.cookiepolicy.egg-info/namespace_packages.txt
tlspu.cookiepolicy.egg-info/not-zip-safe
tlspu.cookiepolicy.egg-info/requires.txt
tlspu.cookiepolicy.egg-info/top_level.txt
tlspu/cookiepolicy/TODO.txt
tlspu/cookiepolicy/__init__.py
tlspu/cookiepolicy/config.py
tlspu/cookiepolicy/configure.zcml
tlspu/cookiepolicy/setuphandlers.py
tlspu/cookiepolicy/testing.py
tlspu/cookiepolicy/update_locales.sh
tlspu/cookiepolicy/Extensions/__init__.py
tlspu/cookiepolicy/Extensions/install.py
tlspu/cookiepolicy/browser/__init__.py
tlspu/cookiepolicy/browser/configure.zcml
tlspu/cookiepolicy/browser/cookiepolicy.py
tlspu/cookiepolicy/browser/viewlets.py
tlspu/cookiepolicy/browser/images/ico-cookiepolicy.png
tlspu/cookiepolicy/browser/js/cookiepolicy.js
tlspu/cookiepolicy/browser/stylesheets/cookiepolicy.css
tlspu/cookiepolicy/browser/templates/cookiepolicy.pt
tlspu/cookiepolicy/controlpanel/__init__.py
tlspu/cookiepolicy/controlpanel/configure.zcml
tlspu/cookiepolicy/controlpanel/cookiepolicy.py
tlspu/cookiepolicy/docs/__init__.py
tlspu/cookiepolicy/docs/browser.txt
tlspu/cookiepolicy/interfaces/__init__.py
tlspu/cookiepolicy/interfaces/cookiepolicy.py
tlspu/cookiepolicy/locales/tlspu.cookiepolicy.pot
tlspu/cookiepolicy/locales/en/LC_MESSAGES/tlspu.cookiepolicy.po
tlspu/cookiepolicy/locales/nl/LC_MESSAGES/tlspu.cookiepolicy.po
tlspu/cookiepolicy/profiles/default/actionicons.xml
tlspu/cookiepolicy/profiles/default/browserlayer.xml
tlspu/cookiepolicy/profiles/default/controlpanel.xml
tlspu/cookiepolicy/profiles/default/cssregistry.xml
tlspu/cookiepolicy/profiles/default/jsregistry.xml
tlspu/cookiepolicy/profiles/default/metadata.xml
tlspu/cookiepolicy/profiles/default/propertiestool.xml
tlspu/cookiepolicy/profiles/default/tlspu.cookiepolicy_install.txt
tlspu/cookiepolicy/profiles/uninstall/browserlayer.xml
tlspu/cookiepolicy/profiles/uninstall/cssregistry.xml
tlspu/cookiepolicy/profiles/uninstall/jsregistry.xml
