Metadata-Version: 1.1
Name: tlspu.cookiepolicy
Version: 1.1.3
Summary: A Plone add-on providing a simple solution to comply with the so called "European Cookie Law".
Home-page: http://www.tlspu.com/consultancy/cookiepolicy
Author: TLSPU
Author-email: contact@tlspu.com
License: AGPL
Keywords: python plone zope cookie eu law
Platform: UNKNOWN
Classifier: Framework :: Plone
Classifier: Framework :: Zope2
Classifier: Programming Language :: Python
Classifier: Topic :: Software Development :: Libraries :: Python Modules
